LICENSE
MANIFEST.in
README.md
requirements.txt
setup.cfg
setup.py
giosgapps_bindings/__init__.py
giosgapps_bindings.egg-info/PKG-INFO
giosgapps_bindings.egg-info/SOURCES.txt
giosgapps_bindings.egg-info/dependency_links.txt
giosgapps_bindings.egg-info/requires.txt
giosgapps_bindings.egg-info/top_level.txt
giosgapps_bindings/django/__init__.py
giosgapps_bindings/django/models.py
giosgapps_bindings/django/services.py
giosgapps_bindings/django/utils.py
giosgapps_bindings/django/views.py
giosgapps_bindings/migrations/0001_initial.py
giosgapps_bindings/migrations/__init__.py
giosgapps_bindings/tests/__init__.py
giosgapps_bindings/tests/test_lib.py
giosgapps_bindings/tests/test_models.py
giosgapps_bindings/tests/urls.py