Metadata-Version: 1.1
Name: giosgapps-bindings
Version: 0.0.21
Summary: Module for Giosg Apps development
Home-page: https://github.com/giosg/giosgapps_bindings
Author: Giosg
Author-email: developers@giosg.com
License: MIT
Download-URL: https://github.com/giosg/giosgapps_bindings/archive/v0.0.21.tar.gz
Keywords: AUTH,GIOSG
Platform: UNKNOWN
Classifier: Development Status :: 3 - Alpha
Classifier: Intended Audience :: Developers
Classifier: Topic :: Software Development :: Build Tools
Classifier: License :: OSI Approved :: MIT License
Classifier: Programming Language :: Python :: 3
Classifier: Programming Language :: Python :: 3.4
Classifier: Programming Language :: Python :: 3.5
Classifier: Programming Language :: Python :: 3.6
